wellnote_downloader/__init__.py
wellnote_downloader-0.13.3.dist-info/LICENSE
wellnote_downloader-0.13.3.dist-info/METADATA
wellnote_downloader-0.13.3.dist-info/WHEEL
wellnote_downloader-0.13.3.dist-info/entry_points.txt
wellnote_downloader-0.13.3.dist-info/top_level.txt
wellnote_downloader-0.13.3.dist-info/RECORD
