Metadata-Version: 2.1
Name: wellnote-downloader
Version: 0.13.3
Summary: Wellnote downloader
Home-page: https://github.com/nogayama/wellnote_downloader
Author: Takahide Nogayama
Author-email: nogayama@gmail.com
Project-URL: Bug Tracker, https://github.com/nogayama/wellnote_downloader/issues
Classifier: Programming Language :: Python :: 3
Classifier: License :: OSI Approved :: MIT License
Classifier: Operating System :: OS Independent
Requires-Python: >=3.6
License-File: LICENSE
Requires-Dist: selenium
Requires-Dist: webdriver-manager
Requires-Dist: filedate
Provides-Extra: test
Requires-Dist: uspec ; extra == 'test'
Requires-Dist: PyHamcrest ; extra == 'test'
